waldur_site_agent_basic_username_management/__init__.py
waldur_site_agent_basic_username_management/backend.py
waldur_site_agent_basic_username_management-0.8.2.dist-info/METADATA
waldur_site_agent_basic_username_management-0.8.2.dist-info/WHEEL
waldur_site_agent_basic_username_management-0.8.2.dist-info/entry_points.txt
waldur_site_agent_basic_username_management-0.8.2.dist-info/RECORD
